{
    "wallpaper": "/home/stefanom/.local/share/Wallpapers/Misc/wp9302457-3440x1440-summer-wallpapers.jpg",
    "alpha": "100",

    "special": {
        "background": "#050305",
        "foreground": "#E1EDF9",
        "cursor": "#E1EDF9"
    },
    "colors": {
        "color0": "#050305",
        "color1": "#435C75",
        "color2": "#566966",
        "color3": "#6F724A",
        "color4": "#607AA2",
        "color5": "#8E8C7F",
        "color6": "#8199B2",
        "color7": "#CDDDEE",
        "color8": "#8F9AA6",
        "color9": "#5A7B9C",
        "color10": "#738C89",
        "color11": "#949963",
        "color12": "#80A3D9",
        "color13": "#BEBBAA",
        "color14": "#ACCDEE",
        "color15": "#A4B0BE"
    }
}
